<!DOCTYPE patchbay>
<patchbay version="0.4.4" name="gdl">
 <output-sockets>
  <socket type="jack-audio" exclusive="off" name="SuperCollider 1" client="SuperCollider">
   <plug>out_1</plug>
   <plug>out_2</plug>
  </socket>
 </output-sockets>
 <input-sockets>
  <socket type="jack-audio" exclusive="off" name="JACK Input Client 1" client="JACK Input Client">
   <plug>in_1</plug>
   <plug>in_2</plug>
  </socket>
 </input-sockets>
 <slots/>
 <cables>
  <cable input="JACK Input Client 1" type="jack-audio" output="SuperCollider 1"/>
 </cables>
</patchbay>

